mullaney_testpkg_a/__init__.py
mullaney_testpkg_a/main_library.py
mullaney_testpkg_a-0.0.1.dist-info/METADATA
mullaney_testpkg_a-0.0.1.dist-info/WHEEL
mullaney_testpkg_a-0.0.1.dist-info/top_level.txt
mullaney_testpkg_a-0.0.1.dist-info/RECORD
