Metadata-Version: 2.1
Name: mullaney-testpkg-a
Version: 0.0.1
Summary: Testing installation of Package
Home-page: https://github.com/mullaneywt/mullaney-testpkg-a
Author: Will Mullaney
Author-email: will.mullaney@gmail.com
License: MIT
Project-URL: Bug Tracker, https://github.com/mullaneywt/mullaney-testpkg-a/issues
Platform: UNKNOWN
Requires-Dist: netaddr
